{"nodes": [{"id": "d_clg_prodectivity_src_router_js", "label": "router.js", "file_type": "code", "source_file": "D:\\clg prodectivity\\src\\router.js", "source_location": "L1"}, {"id": "src_router_routes", "label": "routes", "file_type": "code", "source_file": "D:\\clg prodectivity\\src\\router.js", "source_location": "L4"}, {"id": "src_router_studentroutes", "label": "studentRoutes", "file_type": "code", "source_file": "D:\\clg prodectivity\\src\\router.js", "source_location": "L23"}, {"id": "src_router_adminroutes", "label": "adminRoutes", "file_type": "code", "source_file": "D:\\clg prodectivity\\src\\router.js", "source_location": "L27"}, {"id": "src_router_router", "label": "router", "file_type": "code", "source_file": "D:\\clg prodectivity\\src\\router.js", "source_location": "L33"}], "edges": [{"source": "d_clg_prodectivity_src_router_js", "target": "d_clg_prodectivity_src_main_js", "relation": "imports_from", "context": "import", "confidence": "EXTRACTED", "source_file": "D:\\clg prodectivity\\src\\router.js", "source_location": "L1", "weight": 1.0}, {"source": "d_clg_prodectivity_src_router_js", "target": "src_main_appstate", "relation": "imports", "context": "import", "confidence": "EXTRACTED", "source_file": "D:\\clg prodectivity\\src\\router.js", "source_location": "L1", "weight": 1.0}, {"source": "d_clg_prodectivity_src_router_js", "target": "src_router_routes", "relation": "contains", "confidence": "EXTRACTED", "source_file": "D:\\clg prodectivity\\src\\router.js", "source_location": "L4", "weight": 1.0}, {"source": "d_clg_prodectivity_src_router_js", "target": "src_router_studentroutes", "relation": "contains", "confidence": "EXTRACTED", "source_file": "D:\\clg prodectivity\\src\\router.js", "source_location": "L23", "weight": 1.0}, {"source": "d_clg_prodectivity_src_router_js", "target": "src_router_adminroutes", "relation": "contains", "confidence": "EXTRACTED", "source_file": "D:\\clg prodectivity\\src\\router.js", "source_location": "L27", "weight": 1.0}, {"source": "d_clg_prodectivity_src_router_js", "target": "src_router_router", "relation": "contains", "confidence": "EXTRACTED", "source_file": "D:\\clg prodectivity\\src\\router.js", "source_location": "L33", "weight": 1.0}], "raw_calls": []}