{"nodes": [{"id": "d_clg_prodectivity_src_pages_student_profile_js", "label": "profile.js", "file_type": "code", "source_file": "D:\\clg prodectivity\\src\\pages\\student\\profile.js", "source_location": "L1"}, {"id": "student_profile_render", "label": "render()", "file_type": "code", "source_file": "D:\\clg prodectivity\\src\\pages\\student\\profile.js", "source_location": "L7"}], "edges": [{"source": "d_clg_prodectivity_src_pages_student_profile_js", "target": "d_clg_prodectivity_src_components_sidebar_js", "relation": "imports_from", "context": "import", "confidence": "EXTRACTED", "source_file": "D:\\clg prodectivity\\src\\pages\\student\\profile.js", "source_location": "L1", "weight": 1.0}, {"source": "d_clg_prodectivity_src_pages_student_profile_js", "target": "components_sidebar_createlayout", "relation": "imports", "context": "import", "confidence": "EXTRACTED", "source_file": "D:\\clg prodectivity\\src\\pages\\student\\profile.js", "source_location": "L1", "weight": 1.0}, {"source": "d_clg_prodectivity_src_pages_student_profile_js", "target": "d_clg_prodectivity_src_main_js", "relation": "imports_from", "context": "import", "confidence": "EXTRACTED", "source_file": "D:\\clg prodectivity\\src\\pages\\student\\profile.js", "source_location": "L2", "weight": 1.0}, {"source": "d_clg_prodectivity_src_pages_student_profile_js", "target": "src_main_appstate", "relation": "imports", "context": "import", "confidence": "EXTRACTED", "source_file": "D:\\clg prodectivity\\src\\pages\\student\\profile.js", "source_location": "L2", "weight": 1.0}, {"source": "d_clg_prodectivity_src_pages_student_profile_js", "target": "src_main_showtoast", "relation": "imports", "context": "import", "confidence": "EXTRACTED", "source_file": "D:\\clg prodectivity\\src\\pages\\student\\profile.js", "source_location": "L2", "weight": 1.0}, {"source": "d_clg_prodectivity_src_pages_student_profile_js", "target": "firebase_js", "relation": "imports_from", "context": "import", "confidence": "EXTRACTED", "source_file": "D:\\clg prodectivity\\src\\pages\\student\\profile.js", "source_location": "L3", "weight": 1.0}, {"source": "d_clg_prodectivity_src_pages_student_profile_js", "target": "auth", "relation": "imports_from", "context": "import", "confidence": "EXTRACTED", "source_file": "D:\\clg prodectivity\\src\\pages\\student\\profile.js", "source_location": "L4", "weight": 1.0}, {"source": "d_clg_prodectivity_src_pages_student_profile_js", "target": "supabase_js", "relation": "imports_from", "context": "import", "confidence": "EXTRACTED", "source_file": "D:\\clg prodectivity\\src\\pages\\student\\profile.js", "source_location": "L5", "weight": 1.0}, {"source": "d_clg_prodectivity_src_pages_student_profile_js", "target": "student_profile_render", "relation": "contains", "confidence": "EXTRACTED", "source_file": "D:\\clg prodectivity\\src\\pages\\student\\profile.js", "source_location": "L7", "weight": 1.0}], "raw_calls": [{"caller_nid": "student_profile_render", "callee": "slice", "is_member_call": true, "source_file": "D:\\clg prodectivity\\src\\pages\\student\\profile.js", "source_location": "L10"}, {"caller_nid": "student_profile_render", "callee": "toUpperCase", "is_member_call": true, "source_file": "D:\\clg prodectivity\\src\\pages\\student\\profile.js", "source_location": "L10"}, {"caller_nid": "student_profile_render", "callee": "join", "is_member_call": true, "source_file": "D:\\clg prodectivity\\src\\pages\\student\\profile.js", "source_location": "L10"}, {"caller_nid": "student_profile_render", "callee": "map", "is_member_call": true, "source_file": "D:\\clg prodectivity\\src\\pages\\student\\profile.js", "source_location": "L10"}, {"caller_nid": "student_profile_render", "callee": "split", "is_member_call": true, "source_file": "D:\\clg prodectivity\\src\\pages\\student\\profile.js", "source_location": "L10"}, {"caller_nid": "student_profile_render", "callee": "createLayout", "is_member_call": false, "source_file": "D:\\clg prodectivity\\src\\pages\\student\\profile.js", "source_location": "L13"}, {"caller_nid": "student_profile_render", "callee": "appendChild", "is_member_call": true, "source_file": "D:\\clg prodectivity\\src\\pages\\student\\profile.js", "source_location": "L14"}, {"caller_nid": "student_profile_render", "callee": "querySelector", "is_member_call": true, "source_file": "D:\\clg prodectivity\\src\\pages\\student\\profile.js", "source_location": "L15"}, {"caller_nid": "student_profile_render", "callee": "split", "is_member_call": true, "source_file": "D:\\clg prodectivity\\src\\pages\\student\\profile.js", "source_location": "L45"}, {"caller_nid": "student_profile_render", "callee": "join", "is_member_call": true, "source_file": "D:\\clg prodectivity\\src\\pages\\student\\profile.js", "source_location": "L49"}, {"caller_nid": "student_profile_render", "callee": "slice", "is_member_call": true, "source_file": "D:\\clg prodectivity\\src\\pages\\student\\profile.js", "source_location": "L49"}, {"caller_nid": "student_profile_render", "callee": "split", "is_member_call": true, "source_file": "D:\\clg prodectivity\\src\\pages\\student\\profile.js", "source_location": "L49"}, {"caller_nid": "student_profile_render", "callee": "join", "is_member_call": true, "source_file": "D:\\clg prodectivity\\src\\pages\\student\\profile.js", "source_location": "L62"}, {"caller_nid": "student_profile_render", "callee": "map", "is_member_call": true, "source_file": "D:\\clg prodectivity\\src\\pages\\student\\profile.js", "source_location": "L62"}, {"caller_nid": "student_profile_render", "callee": "join", "is_member_call": true, "source_file": "D:\\clg prodectivity\\src\\pages\\student\\profile.js", "source_location": "L68"}, {"caller_nid": "student_profile_render", "callee": "map", "is_member_call": true, "source_file": "D:\\clg prodectivity\\src\\pages\\student\\profile.js", "source_location": "L68"}, {"caller_nid": "student_profile_render", "callee": "toLocaleDateString", "is_member_call": true, "source_file": "D:\\clg prodectivity\\src\\pages\\student\\profile.js", "source_location": "L129"}, {"caller_nid": "student_profile_render", "callee": "querySelector", "is_member_call": true, "source_file": "D:\\clg prodectivity\\src\\pages\\student\\profile.js", "source_location": "L141"}, {"caller_nid": "student_profile_render", "callee": "querySelector", "is_member_call": true, "source_file": "D:\\clg prodectivity\\src\\pages\\student\\profile.js", "source_location": "L142"}, {"caller_nid": "student_profile_render", "callee": "querySelector", "is_member_call": true, "source_file": "D:\\clg prodectivity\\src\\pages\\student\\profile.js", "source_location": "L143"}, {"caller_nid": "student_profile_render", "callee": "querySelector", "is_member_call": true, "source_file": "D:\\clg prodectivity\\src\\pages\\student\\profile.js", "source_location": "L144"}, {"caller_nid": "student_profile_render", "callee": "querySelector", "is_member_call": true, "source_file": "D:\\clg prodectivity\\src\\pages\\student\\profile.js", "source_location": "L145"}, {"caller_nid": "student_profile_render", "callee": "querySelector", "is_member_call": true, "source_file": "D:\\clg prodectivity\\src\\pages\\student\\profile.js", "source_location": "L146"}, {"caller_nid": "student_profile_render", "callee": "addEventListener", "is_member_call": true, "source_file": "D:\\clg prodectivity\\src\\pages\\student\\profile.js", "source_location": "L148"}, {"caller_nid": "student_profile_render", "callee": "addEventListener", "is_member_call": true, "source_file": "D:\\clg prodectivity\\src\\pages\\student\\profile.js", "source_location": "L188"}, {"caller_nid": "student_profile_render", "callee": "querySelector", "is_member_call": true, "source_file": "D:\\clg prodectivity\\src\\pages\\student\\profile.js", "source_location": "L188"}, {"caller_nid": "student_profile_render", "callee": "querySelector", "is_member_call": true, "source_file": "D:\\clg prodectivity\\src\\pages\\student\\profile.js", "source_location": "L210"}, {"caller_nid": "student_profile_render", "callee": "querySelector", "is_member_call": true, "source_file": "D:\\clg prodectivity\\src\\pages\\student\\profile.js", "source_location": "L211"}, {"caller_nid": "student_profile_render", "callee": "querySelector", "is_member_call": true, "source_file": "D:\\clg prodectivity\\src\\pages\\student\\profile.js", "source_location": "L212"}, {"caller_nid": "student_profile_render", "callee": "querySelector", "is_member_call": true, "source_file": "D:\\clg prodectivity\\src\\pages\\student\\profile.js", "source_location": "L213"}, {"caller_nid": "student_profile_render", "callee": "querySelector", "is_member_call": true, "source_file": "D:\\clg prodectivity\\src\\pages\\student\\profile.js", "source_location": "L214"}, {"caller_nid": "student_profile_render", "callee": "querySelector", "is_member_call": true, "source_file": "D:\\clg prodectivity\\src\\pages\\student\\profile.js", "source_location": "L215"}, {"caller_nid": "student_profile_render", "callee": "querySelector", "is_member_call": true, "source_file": "D:\\clg prodectivity\\src\\pages\\student\\profile.js", "source_location": "L216"}, {"caller_nid": "student_profile_render", "callee": "addEventListener", "is_member_call": true, "source_file": "D:\\clg prodectivity\\src\\pages\\student\\profile.js", "source_location": "L218"}]}